shondesh/__init__.py
shondesh/channels/__init__.py
shondesh/channels/base.py
shondesh/channels/channel_factory.py
shondesh/channels/email.py
shondesh/channels/slack.py
shondesh/channels/telegram.py
shondesh/channels/webhook.py
shondesh/formatters/__init__.py
shondesh/formatters/base_formatter.py
shondesh/formatters/dict_table_formatter.py
shondesh/formatters/slack_message_formatter.py
shondesh/formatters/telegram_message_formatter.py
shondesh/utils/__init__.py
shondesh/utils/constants.py
shondesh-0.1.3.dist-info/LICENSE
shondesh-0.1.3.dist-info/METADATA
shondesh-0.1.3.dist-info/WHEEL
shondesh-0.1.3.dist-info/RECORD
